ass_tag_analyzer/__init__.py
ass_tag_analyzer/ass_format.py
ass_tag_analyzer/ass_parser.py
ass_tag_analyzer/ass_type_parser.py
ass_tag_analyzer/ass_item/__init__.py
ass_tag_analyzer/ass_item/ass_item.py
ass_tag_analyzer/ass_item/ass_tag_alignment.py
ass_tag_analyzer/ass_item/ass_tag_alpha.py
ass_tag_analyzer/ass_item/ass_tag_blur.py
ass_tag_analyzer/ass_item/ass_tag_border.py
ass_tag_analyzer/ass_item/ass_tag_clip.py
ass_tag_analyzer/ass_item/ass_tag_color.py
ass_tag_analyzer/ass_item/ass_tag_fade.py
ass_tag_analyzer/ass_item/ass_tag_font_scale.py
ass_tag_analyzer/ass_item/ass_tag_general.py
ass_tag_analyzer/ass_item/ass_tag_karaoke.py
ass_tag_analyzer/ass_item/ass_tag_position.py
ass_tag_analyzer/ass_item/ass_tag_rotation.py
ass_tag_analyzer/ass_item/ass_tag_shadow.py
ass_tag_analyzer/ass_item/ass_tag_shear.py
ass_tag_analyzer/ass_item/ass_tag_wrap_style.py
ass_tag_analyzer/ass_item/ass_invalid_tag/__init__.py
ass_tag_analyzer/ass_item/ass_invalid_tag/ass_invalid_tag.py
ass_tag_analyzer/ass_item/ass_invalid_tag/ass_invalid_tag_alignment.py
ass_tag_analyzer/ass_item/ass_invalid_tag/ass_invalid_tag_alpha.py
ass_tag_analyzer/ass_item/ass_invalid_tag/ass_invalid_tag_border.py
ass_tag_analyzer/ass_item/ass_invalid_tag/ass_invalid_tag_color.py
ass_tag_analyzer/ass_item/ass_invalid_tag/ass_invalid_tag_font_scale.py
ass_tag_analyzer/ass_item/ass_invalid_tag/ass_invalid_tag_general.py
ass_tag_analyzer/ass_item/ass_invalid_tag/ass_invalid_tag_rotation.py
ass_tag_analyzer/ass_item/ass_invalid_tag/ass_invalid_tag_shadow.py
ass_tag_analyzer/ass_item/ass_invalid_tag/ass_invalid_tag_wrap_style.py
ass_tag_analyzer/ass_item/ass_valid_tag/__init__.py
ass_tag_analyzer/ass_item/ass_valid_tag/ass_valid_tag_alignment.py
ass_tag_analyzer/ass_item/ass_valid_tag/ass_valid_tag_alpha.py
ass_tag_analyzer/ass_item/ass_valid_tag/ass_valid_tag_blur.py
ass_tag_analyzer/ass_item/ass_valid_tag/ass_valid_tag_border.py
ass_tag_analyzer/ass_item/ass_valid_tag/ass_valid_tag_clip.py
ass_tag_analyzer-0.0.5.dist-info/METADATA
ass_tag_analyzer-0.0.5.dist-info/WHEEL
ass_tag_analyzer-0.0.5.dist-info/top_level.txt
ass_tag_analyzer-0.0.5.dist-info/RECORD
