Metadata-Version: 2.4
Name: ass_tag_analyzer
Version: 0.0.5
Summary: Parse .ass tags.
Author-email: moi15moi <moi15moismokerlolilol@gmail.com>
License: MIT
Project-URL: Source, https://github.com/moi15moi/ass_tag_analyzer/
Project-URL: Tracker, https://github.com/moi15moi/ass_tag_analyzer/issues/
Classifier: Development Status :: 4 - Beta
Classifier: Intended Audience :: Other Audience
Classifier: Programming Language :: Python
Classifier: Programming Language :: Python :: 3
Classifier: License :: OSI Approved :: MIT License
Requires-Python: >=3.8
